{
  "id": "ukraine-west",
  "display_name": "Western Ukraine / Border Airspace",
  "series": [
    {
      "date": "2025-05-03",
      "n_hexes": 8,
      "mean_bad_ratio": 0.0504,
      "max_bad_ratio": 0.2632,
      "total_aircraft": 564
    },
    {
      "date": "2025-05-04",
      "n_hexes": 8,
      "mean_bad_ratio": 0.0923,
      "max_bad_ratio": 0.2143,
      "total_aircraft": 643
    },
    {
      "date": "2025-05-05",
      "n_hexes": 8,
      "mean_bad_ratio": 0.0698,
      "max_bad_ratio": 0.2143,
      "total_aircraft": 580
    },
    {
      "date": "2025-05-06",
      "n_hexes": 8,
      "mean_bad_ratio": 0.0714,
      "max_bad_ratio": 0.375,
      "total_aircraft": 572
    },
    {
      "date": "2025-05-07",
      "n_hexes": 7,
      "mean_bad_ratio": 0.033,
      "max_bad_ratio": 0.125,
      "total_aircraft": 564
    },
    {
      "date": "2025-05-08",
      "n_hexes": 8,
      "mean_bad_ratio": 0.0706,
      "max_bad_ratio": 0.3333,
      "total_aircraft": 539
    },
    {
      "date": "2025-06-11",
      "n_hexes": 6,
      "mean_bad_ratio": 0.0155,
      "max_bad_ratio": 0.0333,
      "total_aircraft": 150
    },
    {
      "date": "2025-06-12",
      "n_hexes": 10,
      "mean_bad_ratio": 0.2908,
      "max_bad_ratio": 0.8,
      "total_aircraft": 725
    },
    {
      "date": "2025-06-13",
      "n_hexes": 11,
      "mean_bad_ratio": 0.39,
      "max_bad_ratio": 1.0,
      "total_aircraft": 699
    },
    {
      "date": "2025-06-14",
      "n_hexes": 8,
      "mean_bad_ratio": 0.1602,
      "max_bad_ratio": 0.4545,
      "total_aircraft": 732
    },
    {
      "date": "2025-06-15",
      "n_hexes": 9,
      "mean_bad_ratio": 0.2803,
      "max_bad_ratio": 0.8,
      "total_aircraft": 706
    },
    {
      "date": "2025-06-16",
      "n_hexes": 10,
      "mean_bad_ratio": 0.3695,
      "max_bad_ratio": 0.8,
      "total_aircraft": 717
    },
    {
      "date": "2025-06-17",
      "n_hexes": 10,
      "mean_bad_ratio": 0.2846,
      "max_bad_ratio": 0.7692,
      "total_aircraft": 702
    },
    {
      "date": "2025-06-18",
      "n_hexes": 11,
      "mean_bad_ratio": 0.2795,
      "max_bad_ratio": 0.6,
      "total_aircraft": 771
    },
    {
      "date": "2025-06-19",
      "n_hexes": 9,
      "mean_bad_ratio": 0.2828,
      "max_bad_ratio": 0.8,
      "total_aircraft": 700
    },
    {
      "date": "2025-06-20",
      "n_hexes": 10,
      "mean_bad_ratio": 0.2321,
      "max_bad_ratio": 0.6,
      "total_aircraft": 746
    },
    {
      "date": "2025-07-08",
      "n_hexes": 10,
      "mean_bad_ratio": 0.3087,
      "max_bad_ratio": 0.8333,
      "total_aircraft": 612
    },
    {
      "date": "2025-07-09",
      "n_hexes": 8,
      "mean_bad_ratio": 0.2989,
      "max_bad_ratio": 0.75,
      "total_aircraft": 587
    },
    {
      "date": "2025-07-10",
      "n_hexes": 8,
      "mean_bad_ratio": 0.2219,
      "max_bad_ratio": 0.3333,
      "total_aircraft": 634
    },
    {
      "date": "2025-07-11",
      "n_hexes": 10,
      "mean_bad_ratio": 0.2506,
      "max_bad_ratio": 0.5,
      "total_aircraft": 756
    },
    {
      "date": "2025-07-12",
      "n_hexes": 8,
      "mean_bad_ratio": 0.1151,
      "max_bad_ratio": 0.226,
      "total_aircraft": 730
    },
    {
      "date": "2025-07-13",
      "n_hexes": 9,
      "mean_bad_ratio": 0.1891,
      "max_bad_ratio": 0.6,
      "total_aircraft": 711
    },
    {
      "date": "2025-07-14",
      "n_hexes": 8,
      "mean_bad_ratio": 0.1417,
      "max_bad_ratio": 0.3636,
      "total_aircraft": 662
    },
    {
      "date": "2025-07-15",
      "n_hexes": 9,
      "mean_bad_ratio": 0.1748,
      "max_bad_ratio": 0.3,
      "total_aircraft": 734
    },
    {
      "date": "2025-07-16",
      "n_hexes": 11,
      "mean_bad_ratio": 0.2968,
      "max_bad_ratio": 1.0,
      "total_aircraft": 750
    },
    {
      "date": "2025-07-17",
      "n_hexes": 10,
      "mean_bad_ratio": 0.2418,
      "max_bad_ratio": 0.5,
      "total_aircraft": 712
    },
    {
      "date": "2025-07-18",
      "n_hexes": 9,
      "mean_bad_ratio": 0.2468,
      "max_bad_ratio": 0.7143,
      "total_aircraft": 709
    },
    {
      "date": "2025-07-19",
      "n_hexes": 8,
      "mean_bad_ratio": 0.0956,
      "max_bad_ratio": 0.3333,
      "total_aircraft": 777
    },
    {
      "date": "2025-07-20",
      "n_hexes": 8,
      "mean_bad_ratio": 0.1489,
      "max_bad_ratio": 0.4667,
      "total_aircraft": 792
    },
    {
      "date": "2025-07-21",
      "n_hexes": 10,
      "mean_bad_ratio": 0.1794,
      "max_bad_ratio": 0.4,
      "total_aircraft": 694
    },
    {
      "date": "2025-07-22",
      "n_hexes": 8,
      "mean_bad_ratio": 0.1775,
      "max_bad_ratio": 0.4615,
      "total_aircraft": 730
    },
    {
      "date": "2025-07-23",
      "n_hexes": 8,
      "mean_bad_ratio": 0.1331,
      "max_bad_ratio": 0.4444,
      "total_aircraft": 766
    },
    {
      "date": "2025-07-24",
      "n_hexes": 8,
      "mean_bad_ratio": 0.1268,
      "max_bad_ratio": 0.2727,
      "total_aircraft": 760
    },
    {
      "date": "2025-07-25",
      "n_hexes": 8,
      "mean_bad_ratio": 0.1292,
      "max_bad_ratio": 0.4286,
      "total_aircraft": 721
    },
    {
      "date": "2025-07-26",
      "n_hexes": 10,
      "mean_bad_ratio": 0.2428,
      "max_bad_ratio": 0.8333,
      "total_aircraft": 693
    },
    {
      "date": "2025-07-27",
      "n_hexes": 8,
      "mean_bad_ratio": 0.1348,
      "max_bad_ratio": 0.2246,
      "total_aircraft": 735
    },
    {
      "date": "2025-07-28",
      "n_hexes": 10,
      "mean_bad_ratio": 0.2424,
      "max_bad_ratio": 0.7143,
      "total_aircraft": 669
    },
    {
      "date": "2025-07-29",
      "n_hexes": 11,
      "mean_bad_ratio": 0.2293,
      "max_bad_ratio": 0.5,
      "total_aircraft": 734
    },
    {
      "date": "2025-07-30",
      "n_hexes": 9,
      "mean_bad_ratio": 0.208,
      "max_bad_ratio": 0.5714,
      "total_aircraft": 781
    },
    {
      "date": "2025-07-31",
      "n_hexes": 9,
      "mean_bad_ratio": 0.1954,
      "max_bad_ratio": 0.6,
      "total_aircraft": 784
    },
    {
      "date": "2025-08-01",
      "n_hexes": 11,
      "mean_bad_ratio": 0.2516,
      "max_bad_ratio": 0.7143,
      "total_aircraft": 775
    },
    {
      "date": "2025-08-02",
      "n_hexes": 10,
      "mean_bad_ratio": 0.2592,
      "max_bad_ratio": 0.6667,
      "total_aircraft": 847
    },
    {
      "date": "2025-08-03",
      "n_hexes": 10,
      "mean_bad_ratio": 0.3392,
      "max_bad_ratio": 0.8,
      "total_aircraft": 810
    },
    {
      "date": "2025-08-04",
      "n_hexes": 9,
      "mean_bad_ratio": 0.22,
      "max_bad_ratio": 0.6,
      "total_aircraft": 736
    },
    {
      "date": "2025-08-05",
      "n_hexes": 10,
      "mean_bad_ratio": 0.2154,
      "max_bad_ratio": 0.5,
      "total_aircraft": 752
    },
    {
      "date": "2025-08-06",
      "n_hexes": 8,
      "mean_bad_ratio": 0.124,
      "max_bad_ratio": 0.187,
      "total_aircraft": 756
    },
    {
      "date": "2025-08-07",
      "n_hexes": 9,
      "mean_bad_ratio": 0.1347,
      "max_bad_ratio": 0.6,
      "total_aircraft": 767
    },
    {
      "date": "2025-08-08",
      "n_hexes": 9,
      "mean_bad_ratio": 0.2456,
      "max_bad_ratio": 0.8333,
      "total_aircraft": 805
    },
    {
      "date": "2025-08-09",
      "n_hexes": 9,
      "mean_bad_ratio": 0.2369,
      "max_bad_ratio": 1.0,
      "total_aircraft": 766
    },
    {
      "date": "2025-08-10",
      "n_hexes": 8,
      "mean_bad_ratio": 0.1585,
      "max_bad_ratio": 0.7143,
      "total_aircraft": 760
    },
    {
      "date": "2025-08-11",
      "n_hexes": 9,
      "mean_bad_ratio": 0.1421,
      "max_bad_ratio": 0.4,
      "total_aircraft": 691
    },
    {
      "date": "2025-08-12",
      "n_hexes": 10,
      "mean_bad_ratio": 0.1947,
      "max_bad_ratio": 0.5,
      "total_aircraft": 738
    },
    {
      "date": "2025-08-13",
      "n_hexes": 9,
      "mean_bad_ratio": 0.1562,
      "max_bad_ratio": 0.6,
      "total_aircraft": 725
    },
    {
      "date": "2025-08-14",
      "n_hexes": 11,
      "mean_bad_ratio": 0.1862,
      "max_bad_ratio": 0.4286,
      "total_aircraft": 745
    },
    {
      "date": "2025-08-15",
      "n_hexes": 11,
      "mean_bad_ratio": 0.2698,
      "max_bad_ratio": 0.7143,
      "total_aircraft": 748
    },
    {
      "date": "2025-08-16",
      "n_hexes": 11,
      "mean_bad_ratio": 0.3156,
      "max_bad_ratio": 1.0,
      "total_aircraft": 832
    },
    {
      "date": "2025-08-17",
      "n_hexes": 12,
      "mean_bad_ratio": 0.3828,
      "max_bad_ratio": 1.0,
      "total_aircraft": 740
    },
    {
      "date": "2025-08-18",
      "n_hexes": 10,
      "mean_bad_ratio": 0.2272,
      "max_bad_ratio": 0.4706,
      "total_aircraft": 743
    },
    {
      "date": "2025-08-19",
      "n_hexes": 10,
      "mean_bad_ratio": 0.2677,
      "max_bad_ratio": 0.5714,
      "total_aircraft": 666
    },
    {
      "date": "2025-08-20",
      "n_hexes": 9,
      "mean_bad_ratio": 0.2108,
      "max_bad_ratio": 0.5556,
      "total_aircraft": 725
    },
    {
      "date": "2025-08-21",
      "n_hexes": 8,
      "mean_bad_ratio": 0.1845,
      "max_bad_ratio": 0.3077,
      "total_aircraft": 634
    },
    {
      "date": "2025-08-22",
      "n_hexes": 9,
      "mean_bad_ratio": 0.215,
      "max_bad_ratio": 0.6667,
      "total_aircraft": 701
    },
    {
      "date": "2025-08-23",
      "n_hexes": 10,
      "mean_bad_ratio": 0.1937,
      "max_bad_ratio": 0.5556,
      "total_aircraft": 832
    },
    {
      "date": "2025-08-24",
      "n_hexes": 9,
      "mean_bad_ratio": 0.2208,
      "max_bad_ratio": 0.6364,
      "total_aircraft": 845
    },
    {
      "date": "2025-08-25",
      "n_hexes": 9,
      "mean_bad_ratio": 0.2263,
      "max_bad_ratio": 0.625,
      "total_aircraft": 744
    },
    {
      "date": "2025-08-26",
      "n_hexes": 10,
      "mean_bad_ratio": 0.1895,
      "max_bad_ratio": 0.4,
      "total_aircraft": 764
    },
    {
      "date": "2025-08-27",
      "n_hexes": 9,
      "mean_bad_ratio": 0.3241,
      "max_bad_ratio": 0.8,
      "total_aircraft": 757
    },
    {
      "date": "2025-08-28",
      "n_hexes": 9,
      "mean_bad_ratio": 0.2306,
      "max_bad_ratio": 0.5,
      "total_aircraft": 725
    },
    {
      "date": "2025-08-29",
      "n_hexes": 10,
      "mean_bad_ratio": 0.34,
      "max_bad_ratio": 1.0,
      "total_aircraft": 775
    },
    {
      "date": "2025-08-30",
      "n_hexes": 9,
      "mean_bad_ratio": 0.2575,
      "max_bad_ratio": 0.8,
      "total_aircraft": 775
    },
    {
      "date": "2025-08-31",
      "n_hexes": 9,
      "mean_bad_ratio": 0.2661,
      "max_bad_ratio": 0.6875,
      "total_aircraft": 776
    },
    {
      "date": "2025-09-01",
      "n_hexes": 9,
      "mean_bad_ratio": 0.1629,
      "max_bad_ratio": 0.5,
      "total_aircraft": 783
    },
    {
      "date": "2025-09-02",
      "n_hexes": 9,
      "mean_bad_ratio": 0.2596,
      "max_bad_ratio": 0.5556,
      "total_aircraft": 711
    },
    {
      "date": "2025-09-03",
      "n_hexes": 11,
      "mean_bad_ratio": 0.3495,
      "max_bad_ratio": 0.8,
      "total_aircraft": 669
    },
    {
      "date": "2025-09-04",
      "n_hexes": 9,
      "mean_bad_ratio": 0.2799,
      "max_bad_ratio": 0.7,
      "total_aircraft": 706
    },
    {
      "date": "2025-09-05",
      "n_hexes": 11,
      "mean_bad_ratio": 0.1659,
      "max_bad_ratio": 0.3333,
      "total_aircraft": 800
    },
    {
      "date": "2025-09-06",
      "n_hexes": 9,
      "mean_bad_ratio": 0.3225,
      "max_bad_ratio": 0.7333,
      "total_aircraft": 796
    },
    {
      "date": "2025-09-07",
      "n_hexes": 10,
      "mean_bad_ratio": 0.2846,
      "max_bad_ratio": 0.7143,
      "total_aircraft": 827
    },
    {
      "date": "2025-09-08",
      "n_hexes": 8,
      "mean_bad_ratio": 0.2234,
      "max_bad_ratio": 0.5385,
      "total_aircraft": 758
    },
    {
      "date": "2025-09-09",
      "n_hexes": 9,
      "mean_bad_ratio": 0.3165,
      "max_bad_ratio": 0.7778,
      "total_aircraft": 675
    },
    {
      "date": "2025-09-10",
      "n_hexes": 9,
      "mean_bad_ratio": 0.3372,
      "max_bad_ratio": 0.8571,
      "total_aircraft": 584
    },
    {
      "date": "2025-09-11",
      "n_hexes": 10,
      "mean_bad_ratio": 0.2641,
      "max_bad_ratio": 0.5,
      "total_aircraft": 786
    },
    {
      "date": "2025-09-12",
      "n_hexes": 9,
      "mean_bad_ratio": 0.1905,
      "max_bad_ratio": 0.4286,
      "total_aircraft": 807
    },
    {
      "date": "2025-09-13",
      "n_hexes": 9,
      "mean_bad_ratio": 0.4259,
      "max_bad_ratio": 1.0,
      "total_aircraft": 733
    },
    {
      "date": "2025-09-14",
      "n_hexes": 9,
      "mean_bad_ratio": 0.247,
      "max_bad_ratio": 0.6,
      "total_aircraft": 808
    },
    {
      "date": "2025-09-15",
      "n_hexes": 11,
      "mean_bad_ratio": 0.268,
      "max_bad_ratio": 0.5,
      "total_aircraft": 833
    },
    {
      "date": "2025-09-16",
      "n_hexes": 11,
      "mean_bad_ratio": 0.2676,
      "max_bad_ratio": 0.6,
      "total_aircraft": 787
    },
    {
      "date": "2025-09-17",
      "n_hexes": 9,
      "mean_bad_ratio": 0.2326,
      "max_bad_ratio": 0.5556,
      "total_aircraft": 787
    },
    {
      "date": "2025-09-18",
      "n_hexes": 9,
      "mean_bad_ratio": 0.2488,
      "max_bad_ratio": 0.5714,
      "total_aircraft": 761
    },
    {
      "date": "2025-09-20",
      "n_hexes": 9,
      "mean_bad_ratio": 0.1607,
      "max_bad_ratio": 0.3333,
      "total_aircraft": 760
    },
    {
      "date": "2025-09-21",
      "n_hexes": 9,
      "mean_bad_ratio": 0.2794,
      "max_bad_ratio": 0.5714,
      "total_aircraft": 790
    },
    {
      "date": "2025-09-22",
      "n_hexes": 11,
      "mean_bad_ratio": 0.2707,
      "max_bad_ratio": 0.8,
      "total_aircraft": 746
    },
    {
      "date": "2025-09-23",
      "n_hexes": 10,
      "mean_bad_ratio": 0.307,
      "max_bad_ratio": 0.6667,
      "total_aircraft": 688
    },
    {
      "date": "2025-09-24",
      "n_hexes": 11,
      "mean_bad_ratio": 0.229,
      "max_bad_ratio": 0.5,
      "total_aircraft": 643
    },
    {
      "date": "2025-09-25",
      "n_hexes": 9,
      "mean_bad_ratio": 0.2854,
      "max_bad_ratio": 0.6667,
      "total_aircraft": 697
    },
    {
      "date": "2025-09-26",
      "n_hexes": 11,
      "mean_bad_ratio": 0.3027,
      "max_bad_ratio": 0.6667,
      "total_aircraft": 793
    },
    {
      "date": "2025-09-27",
      "n_hexes": 11,
      "mean_bad_ratio": 0.3483,
      "max_bad_ratio": 0.7143,
      "total_aircraft": 852
    },
    {
      "date": "2025-09-28",
      "n_hexes": 8,
      "mean_bad_ratio": 0.1416,
      "max_bad_ratio": 0.4,
      "total_aircraft": 727
    },
    {
      "date": "2025-09-29",
      "n_hexes": 11,
      "mean_bad_ratio": 0.3084,
      "max_bad_ratio": 0.7333,
      "total_aircraft": 768
    },
    {
      "date": "2025-09-30",
      "n_hexes": 8,
      "mean_bad_ratio": 0.1524,
      "max_bad_ratio": 0.5714,
      "total_aircraft": 726
    },
    {
      "date": "2026-02-21",
      "n_hexes": 8,
      "mean_bad_ratio": 0.1435,
      "max_bad_ratio": 0.3077,
      "total_aircraft": 583
    },
    {
      "date": "2026-02-22",
      "n_hexes": 10,
      "mean_bad_ratio": 0.205,
      "max_bad_ratio": 0.5,
      "total_aircraft": 584
    },
    {
      "date": "2026-02-23",
      "n_hexes": 10,
      "mean_bad_ratio": 0.1835,
      "max_bad_ratio": 0.4,
      "total_aircraft": 562
    },
    {
      "date": "2026-02-24",
      "n_hexes": 8,
      "mean_bad_ratio": 0.1743,
      "max_bad_ratio": 0.5714,
      "total_aircraft": 562
    },
    {
      "date": "2026-02-25",
      "n_hexes": 9,
      "mean_bad_ratio": 0.2219,
      "max_bad_ratio": 0.3529,
      "total_aircraft": 490
    },
    {
      "date": "2026-02-26",
      "n_hexes": 9,
      "mean_bad_ratio": 0.2235,
      "max_bad_ratio": 0.5,
      "total_aircraft": 483
    },
    {
      "date": "2026-02-27",
      "n_hexes": 9,
      "mean_bad_ratio": 0.1996,
      "max_bad_ratio": 0.4615,
      "total_aircraft": 567
    },
    {
      "date": "2026-02-28",
      "n_hexes": 8,
      "mean_bad_ratio": 0.1863,
      "max_bad_ratio": 0.4615,
      "total_aircraft": 502
    },
    {
      "date": "2026-03-01",
      "n_hexes": 8,
      "mean_bad_ratio": 0.2903,
      "max_bad_ratio": 0.6875,
      "total_aircraft": 538
    },
    {
      "date": "2026-03-02",
      "n_hexes": 9,
      "mean_bad_ratio": 0.2659,
      "max_bad_ratio": 0.6667,
      "total_aircraft": 445
    },
    {
      "date": "2026-03-03",
      "n_hexes": 10,
      "mean_bad_ratio": 0.2281,
      "max_bad_ratio": 0.5,
      "total_aircraft": 463
    },
    {
      "date": "2026-03-04",
      "n_hexes": 10,
      "mean_bad_ratio": 0.2307,
      "max_bad_ratio": 0.5,
      "total_aircraft": 562
    },
    {
      "date": "2026-03-05",
      "n_hexes": 10,
      "mean_bad_ratio": 0.161,
      "max_bad_ratio": 0.5294,
      "total_aircraft": 511
    },
    {
      "date": "2026-03-06",
      "n_hexes": 9,
      "mean_bad_ratio": 0.251,
      "max_bad_ratio": 0.5556,
      "total_aircraft": 513
    },
    {
      "date": "2026-03-07",
      "n_hexes": 9,
      "mean_bad_ratio": 0.3106,
      "max_bad_ratio": 0.6471,
      "total_aircraft": 516
    },
    {
      "date": "2026-03-08",
      "n_hexes": 9,
      "mean_bad_ratio": 0.3648,
      "max_bad_ratio": 1.0,
      "total_aircraft": 578
    },
    {
      "date": "2026-03-09",
      "n_hexes": 11,
      "mean_bad_ratio": 0.386,
      "max_bad_ratio": 0.8,
      "total_aircraft": 556
    },
    {
      "date": "2026-03-10",
      "n_hexes": 10,
      "mean_bad_ratio": 0.3394,
      "max_bad_ratio": 0.75,
      "total_aircraft": 589
    },
    {
      "date": "2026-03-11",
      "n_hexes": 9,
      "mean_bad_ratio": 0.0711,
      "max_bad_ratio": 0.1429,
      "total_aircraft": 513
    },
    {
      "date": "2026-03-12",
      "n_hexes": 10,
      "mean_bad_ratio": 0.2452,
      "max_bad_ratio": 0.4615,
      "total_aircraft": 499
    },
    {
      "date": "2026-03-13",
      "n_hexes": 8,
      "mean_bad_ratio": 0.1519,
      "max_bad_ratio": 0.2857,
      "total_aircraft": 481
    },
    {
      "date": "2026-03-14",
      "n_hexes": 8,
      "mean_bad_ratio": 0.1138,
      "max_bad_ratio": 0.3636,
      "total_aircraft": 489
    },
    {
      "date": "2026-03-15",
      "n_hexes": 9,
      "mean_bad_ratio": 0.1497,
      "max_bad_ratio": 0.3636,
      "total_aircraft": 568
    },
    {
      "date": "2026-03-16",
      "n_hexes": 10,
      "mean_bad_ratio": 0.1016,
      "max_bad_ratio": 0.2,
      "total_aircraft": 479
    },
    {
      "date": "2026-03-17",
      "n_hexes": 9,
      "mean_bad_ratio": 0.1304,
      "max_bad_ratio": 0.25,
      "total_aircraft": 487
    },
    {
      "date": "2026-03-18",
      "n_hexes": 9,
      "mean_bad_ratio": 0.1964,
      "max_bad_ratio": 0.4444,
      "total_aircraft": 403
    },
    {
      "date": "2026-03-19",
      "n_hexes": 9,
      "mean_bad_ratio": 0.204,
      "max_bad_ratio": 0.4444,
      "total_aircraft": 453
    },
    {
      "date": "2026-03-20",
      "n_hexes": 9,
      "mean_bad_ratio": 0.1871,
      "max_bad_ratio": 0.4,
      "total_aircraft": 493
    },
    {
      "date": "2026-03-21",
      "n_hexes": 10,
      "mean_bad_ratio": 0.181,
      "max_bad_ratio": 0.4286,
      "total_aircraft": 503
    },
    {
      "date": "2026-03-22",
      "n_hexes": 9,
      "mean_bad_ratio": 0.1901,
      "max_bad_ratio": 0.4286,
      "total_aircraft": 522
    },
    {
      "date": "2026-03-23",
      "n_hexes": 10,
      "mean_bad_ratio": 0.0851,
      "max_bad_ratio": 0.2222,
      "total_aircraft": 484
    },
    {
      "date": "2026-03-24",
      "n_hexes": 8,
      "mean_bad_ratio": 0.048,
      "max_bad_ratio": 0.1087,
      "total_aircraft": 266
    },
    {
      "date": "2026-03-25",
      "n_hexes": 8,
      "mean_bad_ratio": 0.1339,
      "max_bad_ratio": 0.1765,
      "total_aircraft": 557
    },
    {
      "date": "2026-03-26",
      "n_hexes": 8,
      "mean_bad_ratio": 0.1915,
      "max_bad_ratio": 0.3333,
      "total_aircraft": 482
    },
    {
      "date": "2026-03-27",
      "n_hexes": 8,
      "mean_bad_ratio": 0.128,
      "max_bad_ratio": 0.3333,
      "total_aircraft": 496
    },
    {
      "date": "2026-03-28",
      "n_hexes": 8,
      "mean_bad_ratio": 0.1377,
      "max_bad_ratio": 0.2143,
      "total_aircraft": 548
    },
    {
      "date": "2026-03-29",
      "n_hexes": 8,
      "mean_bad_ratio": 0.26,
      "max_bad_ratio": 0.6667,
      "total_aircraft": 490
    },
    {
      "date": "2026-03-30",
      "n_hexes": 10,
      "mean_bad_ratio": 0.0751,
      "max_bad_ratio": 0.1765,
      "total_aircraft": 468
    },
    {
      "date": "2026-03-31",
      "n_hexes": 8,
      "mean_bad_ratio": 0.1525,
      "max_bad_ratio": 0.25,
      "total_aircraft": 540
    },
    {
      "date": "2026-04-01",
      "n_hexes": 8,
      "mean_bad_ratio": 0.2375,
      "max_bad_ratio": 0.5455,
      "total_aircraft": 308
    },
    {
      "date": "2026-04-02",
      "n_hexes": 10,
      "mean_bad_ratio": 0.1927,
      "max_bad_ratio": 0.5,
      "total_aircraft": 448
    },
    {
      "date": "2026-04-03",
      "n_hexes": 11,
      "mean_bad_ratio": 0.3031,
      "max_bad_ratio": 0.8,
      "total_aircraft": 575
    },
    {
      "date": "2026-04-04",
      "n_hexes": 10,
      "mean_bad_ratio": 0.2068,
      "max_bad_ratio": 0.4211,
      "total_aircraft": 586
    },
    {
      "date": "2026-04-05",
      "n_hexes": 9,
      "mean_bad_ratio": 0.2866,
      "max_bad_ratio": 0.5926,
      "total_aircraft": 636
    },
    {
      "date": "2026-04-06",
      "n_hexes": 9,
      "mean_bad_ratio": 0.236,
      "max_bad_ratio": 0.5,
      "total_aircraft": 558
    },
    {
      "date": "2026-04-07",
      "n_hexes": 10,
      "mean_bad_ratio": 0.1525,
      "max_bad_ratio": 0.375,
      "total_aircraft": 588
    },
    {
      "date": "2026-04-08",
      "n_hexes": 9,
      "mean_bad_ratio": 0.2645,
      "max_bad_ratio": 0.5,
      "total_aircraft": 498
    },
    {
      "date": "2026-04-09",
      "n_hexes": 9,
      "mean_bad_ratio": 0.1899,
      "max_bad_ratio": 0.45,
      "total_aircraft": 610
    },
    {
      "date": "2026-04-10",
      "n_hexes": 10,
      "mean_bad_ratio": 0.1568,
      "max_bad_ratio": 0.3529,
      "total_aircraft": 557
    },
    {
      "date": "2026-04-11",
      "n_hexes": 10,
      "mean_bad_ratio": 0.1456,
      "max_bad_ratio": 0.2857,
      "total_aircraft": 697
    },
    {
      "date": "2026-04-12",
      "n_hexes": 10,
      "mean_bad_ratio": 0.328,
      "max_bad_ratio": 0.6667,
      "total_aircraft": 627
    },
    {
      "date": "2026-04-13",
      "n_hexes": 11,
      "mean_bad_ratio": 0.1477,
      "max_bad_ratio": 0.4737,
      "total_aircraft": 576
    },
    {
      "date": "2026-04-14",
      "n_hexes": 9,
      "mean_bad_ratio": 0.3358,
      "max_bad_ratio": 0.8,
      "total_aircraft": 511
    },
    {
      "date": "2026-04-15",
      "n_hexes": 10,
      "mean_bad_ratio": 0.2706,
      "max_bad_ratio": 0.5455,
      "total_aircraft": 546
    },
    {
      "date": "2026-04-16",
      "n_hexes": 11,
      "mean_bad_ratio": 0.2298,
      "max_bad_ratio": 0.4737,
      "total_aircraft": 537
    },
    {
      "date": "2026-04-17",
      "n_hexes": 11,
      "mean_bad_ratio": 0.2181,
      "max_bad_ratio": 0.5,
      "total_aircraft": 586
    },
    {
      "date": "2026-04-18",
      "n_hexes": 10,
      "mean_bad_ratio": 0.1946,
      "max_bad_ratio": 0.4091,
      "total_aircraft": 616
    },
    {
      "date": "2026-04-19",
      "n_hexes": 8,
      "mean_bad_ratio": 0.2117,
      "max_bad_ratio": 0.5833,
      "total_aircraft": 564
    },
    {
      "date": "2026-04-20",
      "n_hexes": 11,
      "mean_bad_ratio": 0.098,
      "max_bad_ratio": 0.2857,
      "total_aircraft": 616
    },
    {
      "date": "2026-04-21",
      "n_hexes": 8,
      "mean_bad_ratio": 0.0889,
      "max_bad_ratio": 0.3077,
      "total_aircraft": 535
    },
    {
      "date": "2026-04-22",
      "n_hexes": 10,
      "mean_bad_ratio": 0.1028,
      "max_bad_ratio": 0.2778,
      "total_aircraft": 555
    },
    {
      "date": "2026-04-23",
      "n_hexes": 9,
      "mean_bad_ratio": 0.0322,
      "max_bad_ratio": 0.0909,
      "total_aircraft": 565
    },
    {
      "date": "2026-04-24",
      "n_hexes": 10,
      "mean_bad_ratio": 0.1006,
      "max_bad_ratio": 0.25,
      "total_aircraft": 636
    },
    {
      "date": "2026-04-25",
      "n_hexes": 10,
      "mean_bad_ratio": 0.0441,
      "max_bad_ratio": 0.1667,
      "total_aircraft": 722
    },
    {
      "date": "2026-04-26",
      "n_hexes": 10,
      "mean_bad_ratio": 0.0382,
      "max_bad_ratio": 0.1111,
      "total_aircraft": 716
    },
    {
      "date": "2026-04-27",
      "n_hexes": 10,
      "mean_bad_ratio": 0.108,
      "max_bad_ratio": 0.3158,
      "total_aircraft": 635
    },
    {
      "date": "2026-04-28",
      "n_hexes": 9,
      "mean_bad_ratio": 0.1528,
      "max_bad_ratio": 0.3636,
      "total_aircraft": 641
    },
    {
      "date": "2026-04-29",
      "n_hexes": 10,
      "mean_bad_ratio": 0.128,
      "max_bad_ratio": 0.2857,
      "total_aircraft": 687
    },
    {
      "date": "2026-04-30",
      "n_hexes": 10,
      "mean_bad_ratio": 0.0689,
      "max_bad_ratio": 0.2,
      "total_aircraft": 322
    },
    {
      "date": "2026-05-01",
      "n_hexes": 10,
      "mean_bad_ratio": 0.1232,
      "max_bad_ratio": 0.2941,
      "total_aircraft": 586
    },
    {
      "date": "2026-05-02",
      "n_hexes": 9,
      "mean_bad_ratio": 0.1223,
      "max_bad_ratio": 0.3333,
      "total_aircraft": 729
    },
    {
      "date": "2026-05-03",
      "n_hexes": 10,
      "mean_bad_ratio": 0.1418,
      "max_bad_ratio": 0.5714,
      "total_aircraft": 742
    },
    {
      "date": "2026-05-04",
      "n_hexes": 9,
      "mean_bad_ratio": 0.1237,
      "max_bad_ratio": 0.4,
      "total_aircraft": 512
    },
    {
      "date": "2026-05-07",
      "n_hexes": 6,
      "mean_bad_ratio": 0.0197,
      "max_bad_ratio": 0.0385,
      "total_aircraft": 180
    },
    {
      "date": "2026-05-08",
      "n_hexes": 11,
      "mean_bad_ratio": 0.0901,
      "max_bad_ratio": 0.2632,
      "total_aircraft": 700
    },
    {
      "date": "2026-05-09",
      "n_hexes": 10,
      "mean_bad_ratio": 0.0629,
      "max_bad_ratio": 0.1818,
      "total_aircraft": 789
    },
    {
      "date": "2026-05-10",
      "n_hexes": 10,
      "mean_bad_ratio": 0.1363,
      "max_bad_ratio": 0.4286,
      "total_aircraft": 796
    },
    {
      "date": "2026-05-11",
      "n_hexes": 12,
      "mean_bad_ratio": 0.1506,
      "max_bad_ratio": 0.4286,
      "total_aircraft": 617
    },
    {
      "date": "2026-05-12",
      "n_hexes": 8,
      "mean_bad_ratio": 0.0947,
      "max_bad_ratio": 0.25,
      "total_aircraft": 614
    },
    {
      "date": "2026-05-13",
      "n_hexes": 10,
      "mean_bad_ratio": 0.2578,
      "max_bad_ratio": 0.5,
      "total_aircraft": 472
    },
    {
      "date": "2026-05-14",
      "n_hexes": 11,
      "mean_bad_ratio": 0.1595,
      "max_bad_ratio": 0.4,
      "total_aircraft": 710
    },
    {
      "date": "2026-05-15",
      "n_hexes": 11,
      "mean_bad_ratio": 0.2631,
      "max_bad_ratio": 1.0,
      "total_aircraft": 681
    },
    {
      "date": "2026-05-16",
      "n_hexes": 11,
      "mean_bad_ratio": 0.2511,
      "max_bad_ratio": 0.5,
      "total_aircraft": 883
    },
    {
      "date": "2026-05-17",
      "n_hexes": 12,
      "mean_bad_ratio": 0.2778,
      "max_bad_ratio": 0.6,
      "total_aircraft": 807
    },
    {
      "date": "2026-05-18",
      "n_hexes": 11,
      "mean_bad_ratio": 0.3691,
      "max_bad_ratio": 0.75,
      "total_aircraft": 741
    },
    {
      "date": "2026-05-19",
      "n_hexes": 11,
      "mean_bad_ratio": 0.3067,
      "max_bad_ratio": 0.625,
      "total_aircraft": 783
    },
    {
      "date": "2026-05-20",
      "n_hexes": 11,
      "mean_bad_ratio": 0.2914,
      "max_bad_ratio": 0.5,
      "total_aircraft": 749
    },
    {
      "date": "2026-05-21",
      "n_hexes": 11,
      "mean_bad_ratio": 0.2323,
      "max_bad_ratio": 0.4,
      "total_aircraft": 764
    },
    {
      "date": "2026-05-22",
      "n_hexes": 10,
      "mean_bad_ratio": 0.1967,
      "max_bad_ratio": 0.4444,
      "total_aircraft": 737
    },
    {
      "date": "2026-05-23",
      "n_hexes": 9,
      "mean_bad_ratio": 0.327,
      "max_bad_ratio": 0.7778,
      "total_aircraft": 775
    },
    {
      "date": "2026-05-24",
      "n_hexes": 11,
      "mean_bad_ratio": 0.2001,
      "max_bad_ratio": 0.5,
      "total_aircraft": 802
    },
    {
      "date": "2026-05-25",
      "n_hexes": 11,
      "mean_bad_ratio": 0.2583,
      "max_bad_ratio": 0.5333,
      "total_aircraft": 777
    },
    {
      "date": "2026-05-26",
      "n_hexes": 11,
      "mean_bad_ratio": 0.3047,
      "max_bad_ratio": 0.6,
      "total_aircraft": 786
    },
    {
      "date": "2026-05-27",
      "n_hexes": 11,
      "mean_bad_ratio": 0.3506,
      "max_bad_ratio": 0.6,
      "total_aircraft": 701
    },
    {
      "date": "2026-05-28",
      "n_hexes": 11,
      "mean_bad_ratio": 0.1922,
      "max_bad_ratio": 0.3929,
      "total_aircraft": 789
    },
    {
      "date": "2026-05-29",
      "n_hexes": 10,
      "mean_bad_ratio": 0.2498,
      "max_bad_ratio": 0.5714,
      "total_aircraft": 763
    },
    {
      "date": "2026-05-30",
      "n_hexes": 11,
      "mean_bad_ratio": 0.3889,
      "max_bad_ratio": 0.6,
      "total_aircraft": 891
    },
    {
      "date": "2026-05-31",
      "n_hexes": 10,
      "mean_bad_ratio": 0.5643,
      "max_bad_ratio": 1.0,
      "total_aircraft": 764
    },
    {
      "date": "2026-06-01",
      "n_hexes": 11,
      "mean_bad_ratio": 0.2442,
      "max_bad_ratio": 0.4583,
      "total_aircraft": 829
    },
    {
      "date": "2026-06-02",
      "n_hexes": 10,
      "mean_bad_ratio": 0.2201,
      "max_bad_ratio": 0.4286,
      "total_aircraft": 819
    },
    {
      "date": "2026-06-03",
      "n_hexes": 10,
      "mean_bad_ratio": 0.4101,
      "max_bad_ratio": 0.76,
      "total_aircraft": 791
    },
    {
      "date": "2026-06-04",
      "n_hexes": 11,
      "mean_bad_ratio": 0.2616,
      "max_bad_ratio": 0.6667,
      "total_aircraft": 808
    },
    {
      "date": "2026-06-05",
      "n_hexes": 10,
      "mean_bad_ratio": 0.1615,
      "max_bad_ratio": 0.3636,
      "total_aircraft": 841
    },
    {
      "date": "2026-06-06",
      "n_hexes": 11,
      "mean_bad_ratio": 0.2257,
      "max_bad_ratio": 0.5455,
      "total_aircraft": 921
    },
    {
      "date": "2026-06-07",
      "n_hexes": 11,
      "mean_bad_ratio": 0.3702,
      "max_bad_ratio": 0.6667,
      "total_aircraft": 919
    },
    {
      "date": "2026-06-08",
      "n_hexes": 11,
      "mean_bad_ratio": 0.2556,
      "max_bad_ratio": 0.4375,
      "total_aircraft": 835
    },
    {
      "date": "2026-06-09",
      "n_hexes": 11,
      "mean_bad_ratio": 0.1925,
      "max_bad_ratio": 0.3143,
      "total_aircraft": 866
    },
    {
      "date": "2026-06-10",
      "n_hexes": 11,
      "mean_bad_ratio": 0.118,
      "max_bad_ratio": 0.25,
      "total_aircraft": 794
    },
    {
      "date": "2026-06-11",
      "n_hexes": 11,
      "mean_bad_ratio": 0.0732,
      "max_bad_ratio": 0.2,
      "total_aircraft": 532
    },
    {
      "date": "2026-06-12",
      "n_hexes": 10,
      "mean_bad_ratio": 0.1509,
      "max_bad_ratio": 0.4211,
      "total_aircraft": 888
    },
    {
      "date": "2026-06-13",
      "n_hexes": 11,
      "mean_bad_ratio": 0.1162,
      "max_bad_ratio": 0.2308,
      "total_aircraft": 980
    },
    {
      "date": "2026-06-14",
      "n_hexes": 11,
      "mean_bad_ratio": 0.1985,
      "max_bad_ratio": 0.3793,
      "total_aircraft": 940
    },
    {
      "date": "2026-06-15",
      "n_hexes": 10,
      "mean_bad_ratio": 0.2393,
      "max_bad_ratio": 0.6667,
      "total_aircraft": 824
    },
    {
      "date": "2026-06-16",
      "n_hexes": 10,
      "mean_bad_ratio": 0.1724,
      "max_bad_ratio": 0.375,
      "total_aircraft": 893
    },
    {
      "date": "2026-06-17",
      "n_hexes": 11,
      "mean_bad_ratio": 0.2803,
      "max_bad_ratio": 0.5,
      "total_aircraft": 914
    },
    {
      "date": "2026-06-18",
      "n_hexes": 12,
      "mean_bad_ratio": 0.2564,
      "max_bad_ratio": 0.6364,
      "total_aircraft": 922
    },
    {
      "date": "2026-06-19",
      "n_hexes": 10,
      "mean_bad_ratio": 0.1568,
      "max_bad_ratio": 0.44,
      "total_aircraft": 853
    },
    {
      "date": "2026-06-20",
      "n_hexes": 11,
      "mean_bad_ratio": 0.3518,
      "max_bad_ratio": 0.8333,
      "total_aircraft": 1005
    },
    {
      "date": "2026-06-21",
      "n_hexes": 10,
      "mean_bad_ratio": 0.4001,
      "max_bad_ratio": 0.8333,
      "total_aircraft": 859
    },
    {
      "date": "2026-06-22",
      "n_hexes": 10,
      "mean_bad_ratio": 0.1579,
      "max_bad_ratio": 0.3793,
      "total_aircraft": 896
    },
    {
      "date": "2026-06-23",
      "n_hexes": 10,
      "mean_bad_ratio": 0.2134,
      "max_bad_ratio": 0.4483,
      "total_aircraft": 891
    },
    {
      "date": "2026-06-24",
      "n_hexes": 11,
      "mean_bad_ratio": 0.2739,
      "max_bad_ratio": 0.5,
      "total_aircraft": 928
    },
    {
      "date": "2026-06-25",
      "n_hexes": 11,
      "mean_bad_ratio": 0.2564,
      "max_bad_ratio": 0.4737,
      "total_aircraft": 964
    },
    {
      "date": "2026-06-26",
      "n_hexes": 10,
      "mean_bad_ratio": 0.2061,
      "max_bad_ratio": 0.5357,
      "total_aircraft": 831
    },
    {
      "date": "2026-06-27",
      "n_hexes": 11,
      "mean_bad_ratio": 0.1591,
      "max_bad_ratio": 0.3462,
      "total_aircraft": 983
    },
    {
      "date": "2026-06-28",
      "n_hexes": 10,
      "mean_bad_ratio": 0.1967,
      "max_bad_ratio": 0.48,
      "total_aircraft": 911
    },
    {
      "date": "2026-06-29",
      "n_hexes": 10,
      "mean_bad_ratio": 0.2009,
      "max_bad_ratio": 0.4444,
      "total_aircraft": 800
    },
    {
      "date": "2026-06-30",
      "n_hexes": 10,
      "mean_bad_ratio": 0.2175,
      "max_bad_ratio": 0.5417,
      "total_aircraft": 782
    },
    {
      "date": "2026-07-01",
      "n_hexes": 10,
      "mean_bad_ratio": 0.1857,
      "max_bad_ratio": 0.4348,
      "total_aircraft": 853
    },
    {
      "date": "2026-07-02",
      "n_hexes": 11,
      "mean_bad_ratio": 0.1935,
      "max_bad_ratio": 0.4242,
      "total_aircraft": 914
    },
    {
      "date": "2026-07-03",
      "n_hexes": 11,
      "mean_bad_ratio": 0.207,
      "max_bad_ratio": 0.4444,
      "total_aircraft": 982
    },
    {
      "date": "2026-07-04",
      "n_hexes": 12,
      "mean_bad_ratio": 0.2892,
      "max_bad_ratio": 1.0,
      "total_aircraft": 1046
    },
    {
      "date": "2026-07-05",
      "n_hexes": 9,
      "mean_bad_ratio": 0.2662,
      "max_bad_ratio": 0.5714,
      "total_aircraft": 889
    },
    {
      "date": "2026-07-06",
      "n_hexes": 11,
      "mean_bad_ratio": 0.174,
      "max_bad_ratio": 0.3704,
      "total_aircraft": 916
    },
    {
      "date": "2026-07-07",
      "n_hexes": 11,
      "mean_bad_ratio": 0.2621,
      "max_bad_ratio": 0.6,
      "total_aircraft": 890
    },
    {
      "date": "2026-07-08",
      "n_hexes": 11,
      "mean_bad_ratio": 0.3819,
      "max_bad_ratio": 0.7273,
      "total_aircraft": 931
    },
    {
      "date": "2026-07-09",
      "n_hexes": 10,
      "mean_bad_ratio": 0.2406,
      "max_bad_ratio": 0.5833,
      "total_aircraft": 951
    },
    {
      "date": "2026-07-10",
      "n_hexes": 11,
      "mean_bad_ratio": 0.2208,
      "max_bad_ratio": 0.5,
      "total_aircraft": 894
    },
    {
      "date": "2026-07-11",
      "n_hexes": 11,
      "mean_bad_ratio": 0.1469,
      "max_bad_ratio": 0.2941,
      "total_aircraft": 990
    },
    {
      "date": "2026-07-12",
      "n_hexes": 11,
      "mean_bad_ratio": 0.2797,
      "max_bad_ratio": 0.5294,
      "total_aircraft": 927
    },
    {
      "date": "2026-07-13",
      "n_hexes": 10,
      "mean_bad_ratio": 0.2263,
      "max_bad_ratio": 0.4444,
      "total_aircraft": 901
    },
    {
      "date": "2026-07-14",
      "n_hexes": 10,
      "mean_bad_ratio": 0.2334,
      "max_bad_ratio": 0.5263,
      "total_aircraft": 863
    },
    {
      "date": "2026-07-15",
      "n_hexes": 10,
      "mean_bad_ratio": 0.3691,
      "max_bad_ratio": 0.6667,
      "total_aircraft": 888
    },
    {
      "date": "2026-07-16",
      "n_hexes": 10,
      "mean_bad_ratio": 0.204,
      "max_bad_ratio": 0.56,
      "total_aircraft": 915
    },
    {
      "date": "2026-07-17",
      "n_hexes": 10,
      "mean_bad_ratio": 0.2999,
      "max_bad_ratio": 0.5455,
      "total_aircraft": 926
    },
    {
      "date": "2026-07-18",
      "n_hexes": 10,
      "mean_bad_ratio": 0.2469,
      "max_bad_ratio": 0.5,
      "total_aircraft": 953
    },
    {
      "date": "2026-07-19",
      "n_hexes": 11,
      "mean_bad_ratio": 0.2944,
      "max_bad_ratio": 0.5455,
      "total_aircraft": 1000
    },
    {
      "date": "2026-07-20",
      "n_hexes": 10,
      "mean_bad_ratio": 0.1888,
      "max_bad_ratio": 0.3636,
      "total_aircraft": 894
    },
    {
      "date": "2026-07-21",
      "n_hexes": 10,
      "mean_bad_ratio": 0.2633,
      "max_bad_ratio": 0.5385,
      "total_aircraft": 929
    }
  ]
}